fast_pdf_extract-0.5.1.dist-info/METADATA
fast_pdf_extract-0.5.1.dist-info/WHEEL
fast_pdf_extract/__init__.py
fast_pdf_extract/fast_pdf_extract.cpython-310-darwin.so
fast_pdf_extract-0.5.1.dist-info/RECORD
